{
    "guideChars": [
        [
            [
                "a",
                "ā",
                "i",
                "ī",
                "u",
                "ū",
                "r̥",
                "r̥̄"
            ],
            [
                "l̥",
                "l̥̄",
                "ē",
                "ai",
                "ō",
                "au"
            ]
        ],
        [
            [
                "e",
                "o",
                "æ",
                "ǣ",
                "ô"
            ]
        ],
        [
            [
                "aṁ",
                "aḥ",
                "am̐"
            ]
        ],
        [
            [
                "ka",
                "kha",
                "ga",
                "gha",
                "ṅa"
            ],
            [
                "ca",
                "cha",
                "ja",
                "jha",
                "ña"
            ],
            [
                "ṭa",
                "ṭha",
                "ḍa",
                "ḍha",
                "ṇa"
            ],
            [
                "ta",
                "tha",
                "da",
                "dha",
                "na"
            ],
            [
                "pa",
                "pha",
                "ba",
                "bha",
                "ma"
            ]
        ],
        [
            [
                "ya",
                "ra",
                "la",
                "va",
                "śa",
                "ṣa",
                "sa",
                "ha"
            ]
        ],
        [
            [
                "ḷa",
                "ḻa",
                "ṟa",
                "ṉa"
            ]
        ],
        [
            [
                "qa",
                "k͟ha",
                "ġa",
                "za",
                "ṛa",
                "ṛha",
                "fa",
                "ẏa"
            ]
        ],
        [
            [
                "n̆ga",
                "n̆ja",
                "n̆ḍa",
                "n̆da",
                "m̆ba"
            ]
        ],
        [
            [
                "ka",
                "kā",
                "ki",
                "kī",
                "ku",
                "kū",
                "kr̥",
                "kr̥̄"
            ],
            [
                "kl̥",
                "kl̥̄",
                "kē",
                "kai",
                "kō",
                "kau"
            ]
        ],
        [
            [
                "ke",
                "ko",
                "kæ",
                "kǣ",
                "kô"
            ]
        ],
        [
            [
                "kaṁ",
                "kaḥ",
                "kam̐",
                "k"
            ]
        ],
        [
            [
                "’",
                "ōṁ",
                ".",
                ".."
            ]
        ]
    ],
    "results": {
        "Ahom": "",
        "Ariyaka": "",
        "Assamese": "",
        "Avestan": "",
        "Balinese": "",
        "BatakKaro": "",
        "BatakManda": "",
        "BatakPakpak": "",
        "BatakSima": "",
        "BatakToba": "",
        "Bengali": "",
        "Bhaiksuki": "",
        "Brahmi": "",
        "Buginese": "",
        "Buhid": "",
        "Burmese": "",
        "Chakma": "",
        "Cham": "",
        "Devanagari": "",
        "Dogra": "",
        "Grantha": "",
        "GranthaPandya": "",
        "Gujarati": "",
        "GunjalaGondi": "",
        "Gurmukhi": "",
        "Hanunoo": "",
        "Javanese": "",
        "Kaithi": "",
        "Kannada": "",
        "KhamtiShan": "",
        "Kharoshthi": "",
        "Khmer": "",
        "Khojki": "",
        "KhomThai": "",
        "Khudawadi": "",
        "Lao": "",
        "LaoPali": "",
        "Lepcha": "",
        "Limbu": "",
        "Mahajani": "",
        "Malayalam": "",
        "MasaramGondi": "",
        "MeeteiMayek": "",
        "Modi": "",
        "Mon": "",
        "Multani": "",
        "Newa": "",
        "OldPersian": "",
        "Oriya": "",
        "PhagsPa": "",
        "Ranjana": "",
        "Rejang": "",
        "Santali": "",
        "Saurashtra": "",
        "Shan": "",
        "Sharada": "",
        "Siddham": "",
        "Sinhala": "",
        "SoraSompeng": "",
        "Soyombo": "",
        "Sundanese": "",
        "SylotiNagri": "",
        "Tagalog": "",
        "Tagbanwa": "",
        "TaiLaing": "",
        "TaiTham": "",
        "Takri": "",
        "Tamil": "",
        "TamilBrahmi": "",
        "TamilGrantha": "",
        "Telugu": "",
        "Thaana": "",
        "Thai": "",
        "Tibetan": "",
        "Tirhuta": "",
        "Urdu": "",
        "Vatteluttu": "",
        "WarangCiti": "",
        "ZanabazarSquare": ""
    },
    "resultsHK": {
        "Ahom": "",
        "Ariyaka": "",
        "Assamese": "",
        "Avestan": "",
        "Balinese": "",
        "BatakKaro": "",
        "BatakManda": "",
        "BatakPakpak": "",
        "BatakSima": "",
        "BatakToba": "",
        "Bengali": "",
        "Bhaiksuki": "",
        "Brahmi": "",
        "Buginese": "",
        "Buhid": "",
        "Burmese": "",
        "Chakma": "",
        "Cham": "",
        "Devanagari": "",
        "Dogra": "",
        "Grantha": "",
        "GranthaPandya": "",
        "Gujarati": "",
        "GunjalaGondi": "",
        "Gurmukhi": "",
        "Hanunoo": "",
        "Javanese": "",
        "Kaithi": "",
        "Kannada": "",
        "KhamtiShan": "",
        "Kharoshthi": "",
        "Khmer": "",
        "Khojki": "",
        "KhomThai": "",
        "Khudawadi": "",
        "Lao": "",
        "LaoPali": "",
        "Lepcha": "",
        "Limbu": "",
        "Mahajani": "",
        "Malayalam": "",
        "MasaramGondi": "",
        "MeeteiMayek": "",
        "Modi": "",
        "Mon": "",
        "Multani": "",
        "Newa": "",
        "OldPersian": "",
        "Oriya": "",
        "PhagsPa": "",
        "Ranjana": "",
        "Rejang": "",
        "Santali": "",
        "Saurashtra": "",
        "Shan": "",
        "Sharada": "",
        "Siddham": "",
        "Sinhala": "",
        "SoraSompeng": "",
        "Soyombo": "",
        "Sundanese": "",
        "SylotiNagri": "",
        "Tagalog": "",
        "Tagbanwa": "",
        "TaiLaing": "",
        "TaiTham": "",
        "Takri": "",
        "Tamil": "",
        "TamilBrahmi": "",
        "TamilGrantha": "",
        "Telugu": "",
        "Thaana": "",
        "Thai": "",
        "Tibetan": "",
        "Tirhuta": "",
        "Urdu": "",
        "Vatteluttu": "",
        "WarangCiti": "",
        "ZanabazarSquare": ""
    }
}