{
    "script1": [
        "ğ¼°",
        "ğ¼±",
        "ğ¼²",
        "ğ¼³",
        "ğ¼´",
        "ğ¼µ",
        "ğ¼¶",
        "ğ¼·",
        "ğ¼¸",
        "ğ¼¹",
        "ğ¼º",
        "ğ¼»",
        "ğ¼¼",
        "ğ¼½",
        "ğ¼¾",
        "ğ¼¿",
        "ğ½€",
        "ğ½",
        "ğ½‚",
        "ğ½ƒ",
        "ğ½„"
    ],
    "script1R": [
        "Ê¾",
        "b",
        "g",
        "h",
        "w",
        "z",
        "á¸¥",
        "y",
        "k",
        "l",
        "m",
        "n",
        "s",
        "Ê¿",
        "p",
        "á¹£",
        "r",
        "Å¡",
        "t",
        "f",
        "lÂ²"
    ],
    "script2": [
        "Ê¾",
        "b",
        "g",
        "h",
        "w",
        "z",
        "á¸¥",
        "y",
        "k",
        "l",
        "m",
        "n",
        "s",
        "Ê¿",
        "p",
        "á¹£",
        "r",
        "Å¡",
        "t",
        "f",
        "lÂ²"
    ],
    "script2R": [
        "ğ¼°",
        "ğ¼±",
        "ğ¼²",
        "ğ¼³",
        "ğ¼´",
        "ğ¼µ",
        "ğ¼¶",
        "ğ¼·",
        "ğ¼¸",
        "ğ¼¹",
        "ğ¼º",
        "ğ¼»",
        "ğ¼¼",
        "ğ¼½",
        "ğ¼¾",
        "ğ¼¿",
        "ğ½€",
        "ğ½",
        "ğ½‚",
        "ğ½ƒ",
        "ğ½„"
    ],
    "scriptLatn": [
        "Ê¾",
        "b",
        "g",
        "h",
        "w",
        "z",
        "á¸¥",
        "y",
        "k",
        "l",
        "m",
        "n",
        "s",
        "Ê¿",
        "p",
        "á¹£",
        "r",
        "Å¡",
        "t",
        "f",
        "lÂ²"
    ]
}